<?xml version="1.0" encoding="UTF-8"?>
<!--Licensed to the Apache Software
	Foundation (ASF) under one or more contributor license agreements. See the
	NOTICE file distributed with this work for additional information regarding
	copyright ownership. The ASF licenses this file to you under the Apache License,
	Version 2.0 (theÃ "License"); you may not use this file except in compliance
	with the License. You may obtain a copy of the License at http://www.apache.org/licenses/LICENSE-2.0
	Unless required by applicable law or agreed to in writing, software distributed
	under the License is distributed on an "AS IS" BASIS, WITHOUT WARRANTIES
	OR CONDITIONS OF ANY ~ KIND, either express or implied. See the License for
	the specific language governing permissions and limitations under the License. -->

<config>
    <client name="acs">
        <logging
                logFileName="../logs/oa4mp.log"
                logName="oa4mp"
                logSize="1000000"
                logFileCount="2"
                debug="true"/>
        <id>myproxy:oa4mp,2012:/client/5a323fc6fcffcff7a95401046a303520</id>
        <serviceUri>https://oa4mp.xsede.org/oauth</serviceUri>
        <callbackUri>https://localhost:8443/credential-store/callback</callbackUri>
        <!--callbackUri>http://149.165.228.118/PHP-Reference-Gateway/xsede_login.php</callbackUri-->
        <lifetime>864000</lifetime>
        <publicKeyFile>/Users/chathuri/dev/airavata/credential-store/oa4mp/oauth-pubkey.pem</publicKeyFile>
        <privateKeyFile>/Users/chathuri/dev/airavata/credential-store/oa4mp/oauth-privkey.pk8</privateKeyFile>
    </client>

    <credential-store>
        <successUri>http://gw120.iu.xsede.org/PHP-Reference-Gateway/</successUri>
        <errorUri>/credential-store/error.jsp</errorUri>
        <redirectUri>/credential-store/show-redirect.jsp</redirectUri>
    </credential-store>

</config>
